pytest_raises/__init__.py
pytest_raises/pytest_raises.py
pytest_raises-0.11.dist-info/LICENSE
pytest_raises-0.11.dist-info/METADATA
pytest_raises-0.11.dist-info/WHEEL
pytest_raises-0.11.dist-info/entry_points.txt
pytest_raises-0.11.dist-info/top_level.txt
pytest_raises-0.11.dist-info/RECORD
