Metadata-Version: 2.1
Name: pytest-raises
Version: 0.11
Summary: An implementation of pytest.raises as a pytest.mark fixture
Home-page: https://github.com/Authentise/pytest-raises
Author: Authentise, Inc.
Author-email: engineering@authentise.com
License: UNKNOWN
Platform: UNKNOWN
Requires-Dist: pytest (>=3.2.2)
Provides-Extra: develop
Requires-Dist: pylint ; extra == 'develop'
Requires-Dist: pytest-cov ; extra == 'develop'
